Metadata-Version: 1.0
Name: ecsentithemelex
Version: 0.0.1
Summary: Russian economic tonal-thematic dictionary
Home-page: https://github.com/ilya013/ecsentithemelex
Author: Ilya Pyltsin
Author-email: ilya.pyltsin@gmail.com
License: UNKNOWN
Platform: UNKNOWN
